jellyserve/__init__.py
jellyserve/_config.py
jellyserve/_exceptions.py
jellyserve/_matchers.py
jellyserve/_middleware.py
jellyserve/_routes.py
jellyserve/_server.py
jellyserve/db.py
jellyserve/internals.py
jellyserve/messages.py
jellyserve/request.py
jellyserve/response.py
jellyserve-0.2.0.dist-info/LICENSE
jellyserve-0.2.0.dist-info/METADATA
jellyserve-0.2.0.dist-info/WHEEL
jellyserve-0.2.0.dist-info/top_level.txt
jellyserve-0.2.0.dist-info/RECORD
