Metadata-Version: 2.1
Name: jellyserve
Version: 0.2.0
Summary: simple python web framework with support for .svelte files
Author-email: Adam Zaoral <the.chosen.zendro@gmail.com>
Project-URL: Homepage, https://github.com/thechosenzendro/jellyserve
Project-URL: Bug Tracker, https://github.com/thechosenzendro/jellyserve/issues
Classifier: Programming Language :: Python :: 3
Classifier: Development Status :: 3 - Alpha
Classifier: License :: OSI Approved :: GNU General Public License (GPL)
Classifier: Operating System :: POSIX :: Linux
Classifier: Intended Audience :: Developers
Classifier: Natural Language :: English
Requires-Python: >=3.10
License-File: LICENSE
